bibleref/__init__.py
bibleref/data.py
bibleref/parser.py
bibleref/ref.py
bibleref/util.py
bibleref-0.16.0.dist-info/LICENSE
bibleref-0.16.0.dist-info/METADATA
bibleref-0.16.0.dist-info/WHEEL
bibleref-0.16.0.dist-info/top_level.txt
bibleref-0.16.0.dist-info/RECORD
