Metadata-Version: 2.1
Name: bibleref
Version: 0.16.0
Summary: A package for handling references to Bible books, verses and verse-ranges.
Project-URL: Documentation, https://multiscript.app/bibleref
Project-URL: Source, https://github.com/multiscript/bibleref
Project-URL: Issue Tracker, https://github.com/multiscript/bibleref/issues
Classifier: Programming Language :: Python :: 3
Classifier: License :: OSI Approved :: MIT License
Classifier: Operating System :: OS Independent
Classifier: Development Status :: 4 - Beta
Classifier: Intended Audience :: Developers
Classifier: Topic :: Religion
Requires-Python: >=3.7
License-File: LICENSE
Requires-Dist: lark >=1.1.5
